rm_measurement/__init__.py
rm_measurement/exceptions.py
rm_measurement/measurement.py
rm_measurement/measurement_types.py
rm_measurement-1.0.0.dist-info/METADATA
rm_measurement-1.0.0.dist-info/WHEEL
rm_measurement-1.0.0.dist-info/licenses/LICENSE
rm_measurement-1.0.0.dist-info/RECORD
