Metadata-Version: 2.4
Name: rm_measurement
Version: 1.0.0
Summary: Defines the Measurement Entity
Author: Robert Mende
License-Expression: MIT
License-File: LICENSE
Classifier: Operating System :: OS Independent
Classifier: Programming Language :: Python :: 3
Requires-Python: >=3.9
